{
    "Header": {
        "profile": "raygen",
        "type": "camPinHole",
        "module": "CamShader.cu",
        "entryFunctionName": "__raygen__pinhole"
    },
    "Data": {
        "Eye": [
            164.5237076120911,
            -121.09156024138929,
            652.0609889929262
        ],
        "Lookat": [
            164.44072651193233,
            -120.9317803308461,
            651.0773302527103
        ],
        "Up": [
            -0.002552352754436926,
            0.9870256879852789,
            0.16054213388579316
        ],
        "radialDistCoeff": [
            0,
            0,
            0
        ],
        "tangDistCoeff": [
            0,
            0,
            0
        ],
        "FovY": 39,
        "Res": [
            6100,
            4256
        ],
        "Name": "1"
    }
}