{
    "Header": {
        "profile": "raygen",
        "type": "camPinHole",
        "module": "CamShader.cu",
        "entryFunctionName": "__raygen__pinhole"
    },
    "Data": {
        "Eye": [
            400.7180498387264,
            -175.54296627767366,
            797.0999033876034
        ],
        "Lookat": [
            400.81817558124004,
            -175.31475715227333,
            796.1314533730078
        ],
        "Up": [
            0.008398965813754397,
            0.9731127215494895,
            0.23017621191557788
        ],
        "radialDistCoeff": [
            0,
            0,
            0
        ],
        "tangDistCoeff": [
            0,
            0,
            0
        ],
        "FovY": 36,
        "Res": [
            6034,
            4012
        ],
        "Name": "13"
    }
}