{
    "Header": {
        "profile": "raygen",
        "type": "camPinHole",
        "module": "CamShader.cu",
        "entryFunctionName": "__raygen__pinhole"
    },
    "Data": {
        "Eye": [
            -6.099374168776789,
            -115.69859550642951,
            614.4276576725513
        ],
        "Lookat": [
            -6.188221059106571,
            -115.50303207412996,
            613.4509995061359
        ],
        "Up": [
            -0.0011391141873281201,
            0.9805153053935666,
            0.19643940110840563
        ],
        "radialDistCoeff": [
            0,
            0,
            0
        ],
        "tangDistCoeff": [
            0,
            0,
            0
        ],
        "FovY": 36,
        "Res": [
            6034,
            4012
        ],
        "Name": "20"
    }
}